pybuild_header_dependency/__init__.py
pybuild_header_dependency/git_downloader.py
pybuild_header_dependency/github_downloader.py
pybuild_header_dependency/gitlab_downloader.py
pybuild_header_dependency/header_resolver.py
pybuild_header_dependency/package_downloader.py
pybuild_header_dependency/pkg_path.py
pybuild_header_dependency/pkgs.json
pybuild_header_dependency/pkgs.py
pybuild_header_dependency/custom_sources/__init__.py
pybuild_header_dependency/custom_sources/boost.py
pybuild_header_dependency-0.1.31.dist-info/LICENSE
pybuild_header_dependency-0.1.31.dist-info/METADATA
pybuild_header_dependency-0.1.31.dist-info/WHEEL
pybuild_header_dependency-0.1.31.dist-info/top_level.txt
pybuild_header_dependency-0.1.31.dist-info/RECORD
